[{
        "pk": 1,
        "model": "courses.course",
        "fields": {
            "sku": 1,
            "name": "Learn Web Designing & HTML5/CSS3 Essentials in 4-Hours",
            "category": 3,
            "price": 75.99,
            "rating": 4.1,
            "image": "html01.jpg",
            "image_url": ""
        }
    },
    {
        "pk": 2,
        "model": "courses.course",
        "fields": {
            "sku": 6,
            "name": "The Complete Bootstrap Masterclass Course - Build 4 Projects",
            "category": 3,
            "price": 199.99,
            "rating": 4.6,
            "image": "bootstrap01.jpg",
            "image_url": ""
            
        }
    },
    {
        "pk": 3,
        "model": "courses.course",
        "fields": {
            "sku": 8,
            "name": "HTML Tutorial: HTML & CSS for Beginners",
            "category": 3,
            "price": 20,
            "rating": 4.6,
            "image": "html02.jpg",
            "image_url": ""
            
        }
    },
    {
        "pk": 4,
        "model": "courses.course",
        "fields": {
            "sku": 18,
            "name": "React JS and Redux - Mastering Web Apps",
            "category": 2,
            "price": 13.99,
            "rating": 4.9,
            "image": "00_react.jpg",
            "image_url": ""
            

        }
    },
    {
        "pk": 5,
        "model": "courses.course",
        "fields": {
            "sku": 28,
           "name": "Javascript ES6! A Complete Reference Guide to Javascript ES6",
            "category": 2,
            "price": 99.99,
            "rating": 4.6,
            "image": "js07.jpg",
            "image_url": ""
            
        }
    },
    {
        "pk": 6,
        "model": "courses.course",
        "fields": {
            "sku": 31,
            "name": "React.js: Building Production Ready Apps, Start to Finish",
            "category": 2,
            "price": 13.99,
            "rating": 4.6,
            "image_url": "",
            "image": "02_react.jpg"
        }
    },
    {
        "pk": 7,
        "model": "courses.course",
        "fields": {
            "sku": 34,
            "name": "Projects in Laravel: Learn Laravel Building 10 Projects",
            "category": 1,
            "price": 49.99,
            "rating": 4.1,
            "image_url": "",
            "image": "laravel01.jpg"
        }
    },
    {
        "pk": 8,
        "model": "courses.course",
        "fields": {
            "sku": 40,
            "name": "Complete React JS web developer with ES6 - Build 10 projects",
            "category": 2,
            "price": 13.99,
            "rating": 4.2,
            "image_url": "",
            "image": "03_react.jpg"
        }
    },
    {
        "pk": 9,
        "model": "courses.course",
        "fields": {
            "sku": 41,
            "name": "Vue JS - Mastering Web Apps",
            "category": 2,
            "price": 13.99,
            "rating": 4.6,
            "image_url": "",
            "image": "vue00.jpg"
           
        }
    },
    {
        "pk": 10,
        "model": "courses.course",
        "fields": {
            "sku": 42,
            "name": "JavaScript the Basics - JavaScript for Beginners",
            "category": 2,
            "price": 13.99,
            "rating": 4.2,
            "image_url": "",
            "image": "js10.jpg"
        }
    },
    {
        "pk": 11,
        "model": "courses.course",
        "fields": {
            "sku": 43,
            "name":"Build a Responsive Website with HTML5, CSS3 and Bootstrap 4",
            "category": 3,
            "price": 13.99,
            "rating": 4.1,
            "image_url": "",
            "image": "html04.jpg"
        }
    },
    {
        "pk": 12,
        "model": "courses.course",
        "fields": {
            "sku": 46,
            "name": "Beginner Full Stack Web Development: HTML, CSS, React & Node",
            "category": 2,
            "price": 99.99,
            "rating": 4.8,
            "image_url": "",
            "image": "html05.jpg"
        }
    },
    {
        "pk": 13,
        "model": "courses.course",
        "fields": {
            "sku": 52,
            "name": "The Complete Web Development Tutorial Using React and Redux",
            "category": 2,
            "price": 13.99,
            "rating": 4.9,
            "image_url": "",
            "image": "04_react.jpg"
        }
    },
    {
        "pk": 14,
        "model": "courses.course",
        "fields": {
            "sku": 57,
            "name": "Getting Started with NodeJS for Beginners",
            "category": 2,
            "price": 99.99,
            "rating": 4.5,
            "image_url": "",
            "image": "nodejs00.jpg"
            
        }
    },
    {
        "pk": 15,
        "model": "courses.course",
        "fields": {
            "sku": 69,
            "name": "React Redux React-Router: From Beginner to Paid Professional",
            "category": 2,
            "price": 13.99,
            "rating": 4.5,
            "image_url": "",
            "image": "react02.jpg"
           
        }
    },
    {
        "pk": 16,
        "model": "courses.course",
        "fields": {
            "sku": 70,
            "name": "Django Core | A Reference Guide to Core Django Concepts",
            "category": 4,
            "price": 119.99,
            "rating": 4.6,
            "image_url": "",
            "image": "django00.jpg"
           
        }
    },
    {
        "pk": 17,
        "model": "courses.course",
        "fields": {
            "sku": 74,
            "name": "Angular 4 Front To Back",
            "category": 2,
            "price": 39.99,
            "rating": 4.6,
            "image_url": "",
            "image": "angular00.jpg"
           
        }
    },
    {
        "pk": 18,
        "model": "courses.course",
        "fields": {
            "sku": 78,
            "name": "JavaScript Game Development: Create Your Own Breakout Game",
            "category": 2,
            "price": 13.99,
            "rating": 4.1,
            "image_url": "",
            "image": "js00.jpg"
            
        }
    },
    {
        "pk": 19,
        "model": "courses.course",
        "fields": {
            "sku": 84,
            "name": "HTML5 and CSS3 for beginners: Create a Website from Scratch",
            "category": 3,
            "price": 13.99,
            "rating": 4.5,
            "image_url": "",
            "image": "html03.jpg"
          
        }
    },
    {
        "pk": 20,
        "model": "courses.course",
        "fields": {
            "sku": 90,
            "name":"Javascript from Beginner to Advanced Level",
            "category": 2,
            "price": 89.99,
            "rating": 4.5,
            "image_url": "",
            "image": "js01.jpg"
            
        }
    },
    {
        "pk": 21,
        "model": "courses.course",
        "fields": {
            "sku": 93,
            "name": "CSS Web Development Crash Course",
            "price": 19.99,
            "category": 3,
            "rating": 4.2,
            "image_url": "",
            "image": "css00.jpg"
            
        }
    },
    {
        "pk": 22,
        "model": "courses.course",
        "fields": {
            "sku": 95,
            "name": "Bootstrap 4: Exploring New Features",
            "category": 3,
            "price": 13.99,
            "rating": 4.4,
            "image_url": "",
            "image": "bootstrap00.jpg"
           
        }
    },
    {
        "pk": 23,
        "model": "courses.course",
        "fields": {
            "sku": 98,
            "name": "PHP with Laravel for beginners - Become a Master in Laravel",
            "category": 1,
            "price": 149.99,
            "rating": 4.1,
           "image_url": "",
            "image": "laravel02.jpg"
           
        }
    },
    {
        "pk": 24,
        "model": "courses.course",
        "fields": {
            "sku": 99,
            "name":"JavaScript 2017: Become Top Rated Web Developer",
            "category": 2,
            "price": 99.99,
             "rating": 5.0,
            "image_url": "https://www.udemy.com/become-professional-javascript-developer/",
            "image": "js02.jpg"
            
        }
    },
    {
        "pk": 25,
        "model": "courses.course",
        "fields": {
            "sku": 103,
            "category": 4,
            "price": 13.99,
            "rating": 4.6,
            "name": "The Ultimate Beginner's Guide to Django",
            "image_url": "",
            "image": "django01.jpg"
          
        }
    },
    {
        "pk": 26,
        "model": "courses.course",
        "fields": {
            "sku": 126,
            "name": "JavaScript Complete for beginners with real world Apps",
            "category": 2,
            "price": 99.99,
            "rating": 5.0,
            "image_url": "",
            "image": "js03.jpg"
          
        }
    },
    {
        "pk": 27,
        "model": "courses.course",
        "fields": {
            "sku": 131,
            "name": "JavaScript Tutorial: Learn JavaScript Code for Beginners",
            "category": 2,
            "price": 19.99,
            "rating": 4.6,
            "image_url": "",
            "image": "js04.jpg"
           
        }
    },
    {
        "pk": 28,
        "model": "courses.course",
        "fields": {
            "sku": 135,
            "name": "The Complete JavaScript, HTML and CSS Tutorial For Beginners",
            "category": 2,
            "price": 39.99,
            "rating": 4.5,
            "image_url": "",
            "image": "js05.jpg"
           
        }
    },
    {
        "pk": 29,
        "model": "courses.course",
        "fields": {
            "sku": 151,
            "name": "Projects In ReactJS - The Complete React Learning Course",
            "category": 2,
            "price": 49.99,
            "rating": 4.5,
            "image_url": "",
            "image": "react00.jpg"
           
        }
    },
    {
        "pk": 30,
        "model": "courses.course",
        "fields": {
            "sku": 167,
            "name": "Learn By Example: The Foundations of HTML, CSS & Javascript",
            "category": 2,
            "price": 49.99,
            "rating": 5.0,
            "image_url": "",
            "image": "html06.jpg"
           
        }
    },
    {
        "pk": 31,
        "model": "courses.course",
        "fields": {
            "sku": 168,
            "name": "JavaScript manipulation of the DOM Document Object Model",
            "category": 2,
            "price": 19.99,
            "rating": 5.0,
            "image_url": "",
            "image": "js05.jpg"
           
        }
    },
    {
        "pk": 32,
        "model": "courses.course",
        "fields": {
            "sku": 169,
            "name":"Learn React JS from scratch",
            "category": 2,
            "price": 99.99,
            "rating": 4.0,
            "image_url": "",
            "image": "react01.jpg"
           
        }
    },
    {
        "pk": 33,
        "model": "courses.course",
        "fields": {
            "sku": 175,
            "name": "Build Your Own Calculator App with Javascript, HTML5 & CSS",
            "category": 2,
            "price": 49.99,
            "rating": 4.0,
            "image_url": "",
            "image": "html07.jpg"
          
        }
    },
    {
        "pk": 34,
        "model": "courses.course",
        "fields": {
            "sku": 182,
            "name":"Introduction to Node.js for Beginners",
            "category": 2,
            "price": 79.99,
            "rating": 4.0,
            "image_url": "",
            "image": "nodejs01.jpg"
            
        }
    },
    {
        "pk": 35,
        "model": "courses.course",
        "fields": {
            "sku": 1023668,
            "name":"Supreme NodeJS Course - For Beginners",
            "category": "2",
            "price": 199.99,
            "rating": 4.8,
            "image_url": "",
            "image": "nodejs02.jpg"
            
        }
    },
    {
        "pk": 36,
        "model": "courses.course",
        "fields": {
            "sku": 822670,
            "name": "JavaScript - Tricks and Workarounds",
            "category": 2,
            "price": 99.99,
            "rating": 4.0,
            "image_url": "",
            "image": "js09.jpg"
            
            }
    },
    {
        "pk": 37,
        "model": "courses.course",
        "fields": {
            "sku": 1051672,
            "name": "Learn PHP from scratch!",
            "category": 1,
            "price": 19.99,
            "rating": 4.0,
            "image_url": "https://www.udemy.com/learn-php-from-scratch-by-niveditajain/",
            "image": "php01.jpg"
           
        }
    },
    {
        "pk": 38,
        "model": "courses.course",
        "fields": {
            "sku": 4104,
            "name": "Laravel, the complete guide with real world projects",
            "category": 1,
            "price": 99.99,
            "rating": 4.1,
            "image_url": "https://www.udemy.com/best-laravel/",
            "image": "laravel00.jpg"
           
        }
    },
    {
        "pk": 39,
        "model": "courses.course",
        "fields": {
            "sku": 900434,
            "name": "VueJS V1 Introduction to VueJS JavaScript Framework",
            "category": 2,
            "price": 99.99,
            "rating": 4.3,
            "image_url": "",
            "image": "vue01.jpg"
          
        }
    },
    {
        "pk": 40,
        "model": "courses.course",
        "fields": {
            "sku": 814206,
            "name": "Learn By Example: PHP For Dynamic Websites",
            "category": 1,
            "price": 49.99,
            "rating": 4.3,
            "image_url": "",
            "image": "php03.jpg"
            }
           
    },
    {
        "pk": 41,
        "model": "courses.course",
        "fields": {
            "sku": 112,
            "name": "Web Design How to Create a Website HTML CSS Bootstrap",
            "category": 3,
            "price": 69.99,
            "rating": 4.4,
            "image_url": "",
             "image": "00_html_css.jpg"
           
        }
    },
    {
        "pk": 42,
        "model": "courses.course",
        "fields": {
            "sku": 71,
            "name": "Master Angular 4 by Example - Build 7 Awesome Apps!",
            "category": 2,
            "price": 119.99,
            "rating": 4.3,
            "image_url": "",
            "image": "angular01.jpg"
           
        }
    },
    {
        "pk": 43,
        "model": "courses.course",
        "fields": {
            "sku": 803378,
            "name": "JavaScript in Action JavaScript Projects",
            "category": 2,
            "price": 149.99,
            "rating": 4.5,
            "image_url": "",
            "image": "js08.jpg"
            
           }
    },
    {
        "pk": 44,
        "model": "courses.course",
        "fields": {
            "sku": 715516,
           "name": "Modern Web Development with Laravel 5.2 (PHP Framework)",
           "category": 1,
            "price": 119.99,
            "rating": 4.2,
            "image_url": "https://www.udemy.com/modern-web-development-with-laravel/",
            "image": "laravel04.jpg"
                    }
            
    },
    {
        "pk": 45,
        "model": "courses.course",
        "fields": {
            "sku": 1047968,
            "name": "Vue JS 2: From Beginner to Professional",
            "image_url": "https://www.udemy.com/vuejs-from-beginner-to-professional/",
            "image": "vue02.jpg",
            "rating": 4.9,
            "category": 2,
            "price": 99.99
            
        }
    },
    {
        "pk": 46,
        "model": "courses.course",
        "fields": {
            "sku": 418386,
            "category": 1,
            "price": 45,
            "rating": 4.9,
            "name": "Create a REAL Social Network like Facebook in PHP + MySQL",
            "image_url": "https://www.udemy.com/make-a-social-media-website/",
            "image": "php00.jpg"
         
            
        }
    },
    {
        "pk": 47,
        "model": "courses.course",
        "fields": {
            "sku": 857270,
            "name": "Become a HTML and CSS Developer - Build a Responsive Site",
            "category": 3,
            "price": 13.99,
            "rating": 5.0,
            "image_url": "",
            "image": "html00.jpg"
            
        }
    }

]